LICENSE
MANIFEST.in
README.md
requirements.txt
setup.py
taleb/AD.py
taleb/ADOSC.py
taleb/ADX.py
taleb/ADXR.py
taleb/APO.py
taleb/DEMA.py
taleb/EMA.py
taleb/KAMA.py
taleb/MA.py
taleb/MAMA.py
taleb/MOM.py
taleb/SMA.py
taleb/TEMA.py
taleb/TRIMA.py
taleb/WMA.py
taleb/__init__.py
taleb/moving_average_type.py
taleb.egg-info/PKG-INFO
taleb.egg-info/SOURCES.txt
taleb.egg-info/dependency_links.txt
taleb.egg-info/not-zip-safe
taleb.egg-info/requires.txt
taleb.egg-info/top_level.txt
tests/ADOSC_tests.py
tests/ADXR_tests.py
tests/ADX_tests.py
tests/AD_tests.py
tests/APO_tests.py
tests/DEMA_tests.py
tests/EMA_tests.py
tests/KAMA_tests.py
tests/MAMA_tests.py
tests/MA_tests.py
tests/MOM_tests.py
tests/SMA_tests.py
tests/TEMA_tests.py
tests/TRIMA_tests.py
tests/WMA_tests.py
tests/__init__.py
tests/data.py