Metadata-Version: 2.1
Name: taleb
Version: 0.0.4
Summary: A pure python version of ta-lib.
Home-page: https://github.com/8W9aG/taleb
Author: Will Sackfield
Author-email: will.sackfield@gmail.com
License: MIT
Keywords: talib ta-lib taleb technical analysis
Classifier: License :: OSI Approved :: MIT License
Classifier: Programming Language :: Python :: 3
License-File: LICENSE
Requires-Dist: numpy>=1.26.4
Requires-Dist: pandas>=2.2.1
Requires-Dist: scipy>=1.12.0
